Workbook

Sheet Vergelijking
A1: Mens vs. AI per accountability — vergelijking tussen organisaties
A2: Facilitator- en Secretaris-rollen uitgesloten. Classificatie = keyword-heuristiek (consistent over alle organisaties); eerste inschatting, te verfijnen.
A4: Organisatie | B4: # accountabilities | C4: AI % | D4: Hybride % | E4: Mens %
A5: Findyourgroup | B5: =COUNTA(Findyourgroup!$D$2:$D$100000) -> 2398 | C5: =COUNTIF(Findyourgroup!$D$2:$D$100000,"AI")/COUNTA(Findyourgroup!$D$2:$D$100000) -> 0.16305254 | D5: =COUNTIF(Findyourgroup!$D$2:$D$100000,"Hybride")/COUNTA(Findyourgroup!$D$2:$D$100000) -> 0.7706422 | E5: =COUNTIF(Findyourgroup!$D$2:$D$100000,"Mens")/COUNTA(Findyourgroup!$D$2:$D$100000) -> 0.066305254
A6: Nooch | B6: =COUNTA(Nooch!$D$2:$D$100000) -> 51 | C6: =COUNTIF(Nooch!$D$2:$D$100000,"AI")/COUNTA(Nooch!$D$2:$D$100000) -> 0.11764706 | D6: =COUNTIF(Nooch!$D$2:$D$100000,"Hybride")/COUNTA(Nooch!$D$2:$D$100000) -> 0.74509804 | E6: =COUNTIF(Nooch!$D$2:$D$100000,"Mens")/COUNTA(Nooch!$D$2:$D$100000) -> 0.1372549
A7: Obelink | B7: =COUNTA(Obelink!$D$2:$D$100000) -> 6760 | C7: =COUNTIF(Obelink!$D$2:$D$100000,"AI")/COUNTA(Obelink!$D$2:$D$100000) -> 0.14511834 | D7: =COUNTIF(Obelink!$D$2:$D$100000,"Hybride")/COUNTA(Obelink!$D$2:$D$100000) -> 0.81153846 | E7: =COUNTIF(Obelink!$D$2:$D$100000,"Mens")/COUNTA(Obelink!$D$2:$D$100000) -> 0.043343195
A8: OVM | B8: =COUNTA(OVM!$D$2:$D$100000) -> 449 | C8: =COUNTIF(OVM!$D$2:$D$100000,"AI")/COUNTA(OVM!$D$2:$D$100000) -> 0.20044543 | D8: =COUNTIF(OVM!$D$2:$D$100000,"Hybride")/COUNTA(OVM!$D$2:$D$100000) -> 0.75946548 | E8: =COUNTIF(OVM!$D$2:$D$100000,"Mens")/COUNTA(OVM!$D$2:$D$100000) -> 0.040089087
A9: Gemiddelde | B9: =AVERAGE(B5:B8) -> 2414.5 | C9: =AVERAGE(C5:C8) -> 0.15656585 | D9: =AVERAGE(D5:D8) -> 0.77168605 | E9: =AVERAGE(E5:E8) -> 0.07174811
A11: Afwijking t.o.v. gemiddelde (procentpunten)
A12: Organisatie | B12: Δ AI | C12: Δ Hybride | D12: Δ Mens
A13: Findyourgroup | B13: =C5-$C$9 -> 0.0064866988 | C13: =D5-$D$9 -> -0.0010438435 | D13: =E5-$E$9 -> -0.0054428552
A14: Nooch | B14: =C6-$C$9 -> -0.038918786 | C14: =D6-$D$9 -> -0.026588006 | D14: =E6-$E$9 -> 0.065506792
A15: Obelink | B15: =C7-$C$9 -> -0.011447502 | C15: =D7-$D$9 -> 0.039852416 | D15: =E7-$E$9 -> -0.028404914
A16: OVM | B16: =C8-$C$9 -> 0.043879589 | C16: =D8-$D$9 -> -0.012220567 | D16: =E8-$E$9 -> -0.031659023

Sheet Findyourgroup
A1: Cirkel | B1: Rol | C1: Accountability | D1: Uitvoerder | E1: AI-rijpheid | F1: Waarom
A2: — | B2: Findyourgroup | C2: Ondersteunen bij positionering en strategische richting | D2: Hybride | E2: Begeleid | F2: AI doet het voorwerk; de rolhouder beslist of doet het relationele/fysieke deel.
A3: — | B3: Findyourgroup | C3: Ondersteunen bij procesoptimalisatie en schaalbaarheid | D3: Hybride | E3: Begeleid | F3: AI doet het voorwerk; de rolhouder beslist of doet het relationele/fysieke deel.
A4: — | B4: Findyourgroup | C4: Vormgeven van juridische kaders en risicobeheersing | D4: Mens | E4: - | F4: Relationeel/juridisch/zeggenschap: blijft bij de rolhouder.
A5: — | B5: Findyourgroup | C5: Faciliteren digitale strategie, ai en automatisering | D5: Hybride | E5: Begeleid | F5: AI doet het voorwerk; de rolhouder beslist of doet het relationele/fysieke deel.
A6: — | B6: Findyourgroup | C6: Faciliteren in complexe HR vraagstukken en ontwikkeling van medewerkers | D6: Hybride | E6: Begeleid | F6: AI doet het voorwerk; de rolhouder beslist of doet het relationele/fysieke deel.
A7: — | B7: Findyourgroup | C7: Zorg dragen voor management rapportage en informatie | D7: Hybride | E7: Begeleid | F7: AI doet het voorwerk; de rolhouder beslist of doet het relationele/fysieke deel.
A8: — | B8: Findyourgroup | C8: Coachen op ondernemers vraagstukken | D8: Mens | E8: - | F8: Relationeel/juridisch/zeggenschap: blijft bij de rolhouder.
A9: Findyourgroup | B9: Business Spain | C9: identifying opportunities in the Spanish market for the group | D9: Hybride | E9: Begeleid | F9: AI doet het voorwerk; de rolhouder beslist of doet het relationele/fysieke deel.
A10: Findyourgroup | B10: Business Spain | C10: Develop business in SPain | D10: Hybride | E10: Begeleid | F10: AI doet het voorwerk; de rolhouder beslist of doet het relationele/fysieke deel.
A11: Findyourgroup | B11: Business Spain | C11: Inform leadlinks of the developement of their businesses in Spain | D11: Hybride | E11: Begeleid | F11: AI doet het voorwerk; de rolhouder beslist of doet het relationele/fysieke deel.
A12: Findyourgroup | B12: Juridisch | C12: Doornemen en adviseren juridische documentatie | D12: Mens | E12: - | F12: Relationeel/juridisch/zeggenschap: blijft bij de rolhouder.
... A2399: Operationele cirkel Werkplekmeesters | B2399: Werkkleding | C2399: Bestellen geschikte werkkleding | D2399: Hybride | E2399: Begeleid | F2399: AI doet het voorwerk; de rolhouder beslist of doet het relationele/fysieke deel.

Sheet Nooch
A1: Cirkel | B1: Rol | C1: Accountability | D1: Uitvoerder | E1: AI-rijpheid | F1: Waarom
A2: Nooch | B2: Brand & Visual Designer | C2: Creating all visual assets (ads, socials, emails, packaging, etc.) | D2: Hybride | E2: Begeleid | F2: AI doet het voorwerk; de rolhouder beslist of doet het relationele/fysieke deel.
A3: Nooch | B3: Brand & Visual Designer | C3: Maintaining and evolving the Nooch visual identity | D3: Hybride | E3: Begeleid | F3: AI doet het voorwerk; de rolhouder beslist of doet het relationele/fysieke deel.
A4: Nooch | B4: Brand & Visual Designer | C4: Producing brand materials for marketing & community | D4: Hybride | E4: Begeleid | F4: AI doet het voorwerk; de rolhouder beslist of doet het relationele/fysieke deel.
A5: Nooch | B5: Brand & Visual Designer | C5: Providing visuals for website and product page | D5: Hybride | E5: Begeleid | F5: AI doet het voorwerk; de rolhouder beslist of doet het relationele/fysieke deel.
A6: Nooch | B6: Brand & Visual Designer | C6: Keeping all brand files organised and accessible | D6: Hybride | E6: Begeleid | F6: AI doet het voorwerk; de rolhouder beslist of doet het relationele/fysieke deel.
A7: Nooch | B7: Carbon Footprint Improver | C7: Maintaining comprehensive insight into the Carbon Footprint of all Nooch products. | D7: Hybride | E7: Begeleid | F7: AI doet het voorwerk; de rolhouder beslist of doet het relationele/fysieke deel.
A8: Nooch | B8: Carbon Footprint Improver | C8: Identifying and executing opportunities to continuously lower the carbon footprint. | D8: Hybride | E8: Begeleid | F8: AI doet het voorwerk; de rolhouder beslist of doet het relationele/fysieke deel.
A9: Nooch | B9: Carbon Footprint Improver | C9: Collaborating with other roles to balance sustainability with cost and speed. | D9: Hybride | E9: Begeleid | F9: AI doet het voorwerk; de rolhouder beslist of doet het relationele/fysieke deel.
A10: Nooch | B10: Circle Rep | C10: Seeking to understand Tensions conveyed by Role Leads within the Circle | D10: Hybride | E10: Begeleid | F10: AI doet het voorwerk; de rolhouder beslist of doet het relationele/fysieke deel.
A11: Nooch | B11: Circle Rep | C11: Discerning Tensions appropriate to process within a broader Circle that holds the Circle | D11: Hybride | E11: Begeleid | F11: AI doet het voorwerk; de rolhouder beslist of doet het relationele/fysieke deel.
A12: Nooch | B12: Circle Rep | C12: Processing Tensions within a broader Circle to remove constraints on the Circle | D12: AI | E12: Nu | F12: Data-/proceswerk ('processing'): te automatiseren door een agent.
... A52: Mother Earth | B52: Shareholder | C52: Signing document for legal responsibility | D52: Mens | E52: - | F52: Relationeel/juridisch/zeggenschap: blijft bij de rolhouder.

Sheet Obelink
A1: Cirkel | B1: Rol | C1: Accountability | D1: Uitvoerder | E1: AI-rijpheid | F1: Waarom
A2: — | B2: Familiebedrijf | C2: Bepalen en doorontwikkelen van de missie van de organisatie | D2: Hybride | E2: Begeleid | F2: AI doet het voorwerk; de rolhouder beslist of doet het relationele/fysieke deel.
A3: — | B3: Familiebedrijf | C3: Aanwijzen van de juiste Lead Link voor de @Bedrijfscirkel | D3: Hybride | E3: Begeleid | F3: AI doet het voorwerk; de rolhouder beslist of doet het relationele/fysieke deel.
A4: — | B4: Familiebedrijf | C4: Formuleren van verantwoordelijkheden voor de Bedrijfscirkel | D4: Hybride | E4: Begeleid | F4: AI doet het voorwerk; de rolhouder beslist of doet het relationele/fysieke deel.
A5: Familiebedrijf | B5: Directielid | C5: Goedkeuren van begroting van @Bedrijfscirkel | D5: Hybride | E5: Begeleid | F5: AI doet het voorwerk; de rolhouder beslist of doet het relationele/fysieke deel.
A6: Familiebedrijf | B6: Directielid | C6: Plaatsen van handtekening op formeel juridische stukken | D6: Mens | E6: - | F6: Relationeel/juridisch/zeggenschap: blijft bij de rolhouder.
A7: Familiebedrijf | B7: Directielid | C7: Verlenen van decharge | D7: Hybride | E7: Begeleid | F7: AI doet het voorwerk; de rolhouder beslist of doet het relationele/fysieke deel.
A8: Familiebedrijf | B8: Lead Link | C8: Toewijzen van partners aan de rollen van de cirkel; monitoren van de rolgeschiktheid; geven van feedback om de rolgeschiktheid te verbeteren; en zo nodig het opnieuw toewijzen van rollen aan andere partners om de rolgeschiktheid te verbeteren | D8: Hybride | E8: Begeleid | F8: AI doet het voorwerk; de rolhouder beslist of doet het relationele/fysieke deel.
A9: Familiebedrijf | B9: Lead Link | C9: Verdelen van de middelen van de cirkel over haar diverse projecten en/of rollen | D9: Hybride | E9: Begeleid | F9: AI doet het voorwerk; de rolhouder beslist of doet het relationele/fysieke deel.
A10: Familiebedrijf | B10: Lead Link | C10: Bepalen van prioriteiten en strategieën voor de cirkel | D10: Hybride | E10: Begeleid | F10: AI doet het voorwerk; de rolhouder beslist of doet het relationele/fysieke deel.
A11: Familiebedrijf | B11: Lead Link | C11: Bepalen van indicatoren voor de cirkel | D11: Hybride | E11: Begeleid | F11: AI doet het voorwerk; de rolhouder beslist of doet het relationele/fysieke deel.
A12: Familiebedrijf | B12: Lead Link | C12: Structureren van de governance van de cirkel om invulling te geven aan zijn purpose en verantwoordelijkheden | D12: Hybride | E12: Begeleid | F12: AI doet het voorwerk; de rolhouder beslist of doet het relationele/fysieke deel.
... A6761: Team van de toekomst | B6761: Wij-gevoel | C6761: Stimuleren/adviseren van cultuurverhogende activiteiten | D6761: Mens | E6761: - | F6761: Relationeel/juridisch/zeggenschap: blijft bij de rolhouder.

Sheet OVM
A1: Cirkel | B1: Rol | C1: Accountability | D1: Uitvoerder | E1: AI-rijpheid | F1: Waarom
A2: Onlineveilingmeester.nl | B2: CISO | C2: Ontwikkelen en beheren van informatiebeveiligingsbeleid, -richtlijnen en processen. | D2: Hybride | E2: Begeleid | F2: AI doet het voorwerk; de rolhouder beslist of doet het relationele/fysieke deel.
A3: Onlineveilingmeester.nl | B3: CISO | C3: Controleren van naleving van informatiebeveiligingsafspraken. | D3: AI | E3: Nu | F3: Data-/proceswerk ('controleren'): te automatiseren door een agent.
A4: Onlineveilingmeester.nl | B4: CISO | C4: Identificeren en mitigeren van informatiebeveiligingsrisico’s. | D4: Hybride | E4: Begeleid | F4: AI doet het voorwerk; de rolhouder beslist of doet het relationele/fysieke deel.
A5: Onlineveilingmeester.nl | B5: CISO | C5: Uitvoeren van risicoanalyse en adviseren over verbeteringen. | D5: Hybride | E5: Begeleid | F5: AI doet het voorwerk; de rolhouder beslist of doet het relationele/fysieke deel.
A6: Onlineveilingmeester.nl | B6: CISO | C6: Monitoren van beveiligingsincidenten en coördineren van respons bij beveiligingsinbreuk en datalekken. | D6: AI | E6: Nu | F6: Data-/proceswerk ('monitoren'): te automatiseren door een agent.
A7: Onlineveilingmeester.nl | B7: CISO | C7: Creeëren van bewustwording van medewerkers over cyberdreigingen zoals phishing. | D7: Hybride | E7: Begeleid | F7: AI doet het voorwerk; de rolhouder beslist of doet het relationele/fysieke deel.
A8: Onlineveilingmeester.nl | B8: CISO | C8: Begeleiden van audits en houden van toezicht op beveiligingsincidenten. | D8: Hybride | E8: Begeleid | F8: AI doet het voorwerk; de rolhouder beslist of doet het relationele/fysieke deel.
A9: Onlineveilingmeester.nl | B9: CISO | C9: Samenwerken met IT en management om dataveiligheid te waarborgen. | D9: Hybride | E9: Begeleid | F9: AI doet het voorwerk; de rolhouder beslist of doet het relationele/fysieke deel.
A10: Onlineveilingmeester.nl | B10: CISO | C10: Aanspreekpunt zijn voor informatiebeveiliging en ondersteunen van medewerkers bij beveiligingsvragen. | D10: Hybride | E10: Begeleid | F10: AI doet het voorwerk; de rolhouder beslist of doet het relationele/fysieke deel.
A11: Onlineveilingmeester.nl | B11: Cirkel Rep | C11: Proberen om de Spanningen van Rol Leads binnen de Cirkel te begrijpen | D11: Hybride | E11: Begeleid | F11: AI doet het voorwerk; de rolhouder beslist of doet het relationele/fysieke deel.
A12: Onlineveilingmeester.nl | B12: Cirkel Rep | C12: Beoordelen welke Spanningen geschikt zijn om te behandelen in een bredere Cirkel | D12: Hybride | E12: Begeleid | F12: AI doet het voorwerk; de rolhouder beslist of doet het relationele/fysieke deel.
... A450: Tuincentrum Hardenberg | B450: Mailbox | C450: Communiceren met klanten over financiële vraagstukken | D450: Hybride | E450: Begeleid | F450: AI doet het voorwerk; de rolhouder beslist of doet het relationele/fysieke deel.

Sheet Methode
A1: Methode
A2: Bron: GlassFrog governance-export per organisatie (NL of EN).
A3: Facilitator- en Secretaris/Secretary-rollen zijn uitgesloten (procesrollen).
A5: Classificatie per accountability:
A6: AI = data-/proceswerk dat een agent binnen de rol autonoom kan doen.
A7: Hybride = de agent doet het voorwerk; de mens (rolhouder) beslist of voert het
A8: relationele/fysieke deel uit.
A9: Mens = relationeel, juridisch, fysiek of zeggenschap; blijft bij de rolhouder.
A11: De classificatie is een keyword-heuristiek: een consistente eerste inschatting,
A12: bedoeld om samen te verfijnen. 'Hybride' is de vergaarbak; 'Mens' is een ondergrens.
A13: Omdat hetzelfde recept over alle organisaties draait, is de vergelijking eerlijk.
A15: Visie: de rol blijft van een mens; AI-agents pakken binnen de rol specifieke
A16: accountabilities op. Dit overzicht is de kaart daarvoor.
